schwimmbad/__init__.py
schwimmbad/_test_helpers.py
schwimmbad/_version.py
schwimmbad/decorators.py
schwimmbad/error.py
schwimmbad/jl.py
schwimmbad/mpi.py
schwimmbad/multiprocessing.py
schwimmbad/pool.py
schwimmbad/serial.py
schwimmbad/utils.py
schwimmbad-0.4.1.dist-info/METADATA
schwimmbad-0.4.1.dist-info/WHEEL
schwimmbad-0.4.1.dist-info/licenses/LICENSE
schwimmbad-0.4.1.dist-info/RECORD
