Metadata-Version: 2.1
Name: schwimmbad
Version: 0.4.1
Summary: A common interface for parallel processing pools.
Project-URL: Homepage, https://github.com/adrn/schwimmbad
Project-URL: Bug Tracker, https://github.com/adrn/schwimmbad/issues
Project-URL: Discussions, https://github.com/adrn/schwimmbad/discussions
Project-URL: Changelog, https://github.com/adrn/schwimmbad/releases
Author-email: Adrian Price-Whelan <adrianmpw@gmail.com>
License: MIT License
License-File: LICENSE
Requires-Python: >=3.9
Requires-Dist: dill
Requires-Dist: multiprocess
Provides-Extra: all
Requires-Dist: joblib; extra == 'all'
Requires-Dist: mpi4py; extra == 'all'
Provides-Extra: docs
Requires-Dist: emcee; extra == 'docs'
Requires-Dist: matplotlib; extra == 'docs'
Requires-Dist: pydata-sphinx-theme; extra == 'docs'
Requires-Dist: sphinx-autodoc-typehints; extra == 'docs'
Requires-Dist: sphinx-automodapi; extra == 'docs'
Requires-Dist: sphinx-copybutton; extra == 'docs'
Requires-Dist: sphinx>=7.0; extra == 'docs'
Provides-Extra: test
Requires-Dist: pytest-astropy; extra == 'test'
Requires-Dist: pytest-cov>=3; extra == 'test'
Requires-Dist: pytest>=6; extra == 'test'
Requires-Dist: schwimmbad[all]; extra == 'test'
